hue_entertainment_pykit/__init__.py
hue_entertainment_pykit/api.py
hue_entertainment_pykit/bridge/__init__.py
hue_entertainment_pykit/bridge/bridge_repository.py
hue_entertainment_pykit/bridge/entertainment_configuration_repository.py
hue_entertainment_pykit/exceptions/__init__.py
hue_entertainment_pykit/exceptions/api_exception.py
hue_entertainment_pykit/exceptions/bridge_exception.py
hue_entertainment_pykit/exceptions/dtls_handshake_exception.py
hue_entertainment_pykit/models/__init__.py
hue_entertainment_pykit/models/bridge.py
hue_entertainment_pykit/models/entertainment_configuration.py
hue_entertainment_pykit/models/payload.py
hue_entertainment_pykit/network/__init__.py
hue_entertainment_pykit/network/dtls.py
hue_entertainment_pykit/network/mdns.py
hue_entertainment_pykit/services/__init__.py
hue_entertainment_pykit/services/discovery_service.py
hue_entertainment_pykit/services/streaming_service.py
hue_entertainment_pykit/utils/__init__.py
hue_entertainment_pykit/utils/converter.py
hue_entertainment_pykit/utils/file_handler.py
hue_entertainment_pykit/utils/logger.py
hue_entertainment_pykit/utils/status_code.py
hue_entertainment_pykit-0.9.4.dist-info/licenses/LICENSE.md
hue_entertainment_pykit-0.9.4.dist-info/METADATA
hue_entertainment_pykit-0.9.4.dist-info/WHEEL
hue_entertainment_pykit-0.9.4.dist-info/top_level.txt
hue_entertainment_pykit-0.9.4.dist-info/RECORD
