Metadata-Version: 2.4
Name: hue-entertainment-pykit
Version: 0.9.4
Summary: A comprehensive Python toolkit for Philips Hue Entertainment API
Author: Dominik Hrdas
License-Expression: MIT
Project-URL: Repository, https://github.com/hrdasdominik/hue-entertainment-pykit
Keywords: philips,hue,lights,entertainment,api
Classifier: Programming Language :: Python :: 3.10
Classifier: Programming Language :: Python :: 3.11
Classifier: Programming Language :: Python :: 3.12
Classifier: Operating System :: OS Independent
Classifier: Topic :: Utilities
Requires-Python: <3.13,>=3.10
License-File: LICENSE.md
Requires-Dist: python-mbedtls<3,>=2.10.1
Requires-Dist: requests<3,>=2.32.5
Requires-Dist: typing_extensions<5,>=4.8.0; python_version < "3.11"
Requires-Dist: zeroconf<1,>=0.148.0
Provides-Extra: dev
Requires-Dist: flake8<8,>=7; extra == "dev"
Requires-Dist: pylint<5,>=4; extra == "dev"
Dynamic: license-file
